LICENSE
MANIFEST.in
NOTICE
Pipfile
Pipfile.lock
README.md
setup.py
cdislogging/__init__.py
cdislogging.egg-info/PKG-INFO
cdislogging.egg-info/SOURCES.txt
cdislogging.egg-info/dependency_links.txt
cdislogging.egg-info/top_level.txt