Metadata-Version: 1.0
Name: cdislogging
Version: 1.0.0
Summary: Standardized logging tool and format for cdis applications
Home-page: UNKNOWN
Author: UNKNOWN
Author-email: UNKNOWN
License: Apache
Platform: UNKNOWN
